sys_backlight/__init__.py
sys_backlight/backlight/__init__.py
sys_backlight/console/__init__.py
sys_backlight/ncurses/__init__.py
sys_backlight/pyqt/__init__.py
sys_backlight-0.1.dist-info/DESCRIPTION.rst
sys_backlight-0.1.dist-info/LICENSE.txt
sys_backlight-0.1.dist-info/METADATA
sys_backlight-0.1.dist-info/RECORD
sys_backlight-0.1.dist-info/WHEEL
sys_backlight-0.1.dist-info/entry_points.txt
sys_backlight-0.1.dist-info/metadata.json
sys_backlight-0.1.dist-info/top_level.txt
